{"title":"FuckinVan.14.08.26.Lucia.Dinamita.Shes.Pure.Dynamite.XXX.SD.MP4-","uid":10925424,"size":370555135,"categoryP":"porn","categoryS":"other","magnet":"?xt=urn:btih:0711c6896c3a93f19b4436fc4c465decdae644b8&amp;dn=FuckinVan.14.08.26.Lucia.Dinamita.Shes.Pure.Dynamite.XXX.SD.MP4-&amp;tr=udp%3A%2F%2Ftracker.openbittorrent.com%3A80&amp;tr=udp%3A%2F%2Fopen.demonii.com%3A1337&amp;tr=udp%3A%2F%2Ftracker.coppersurfer.tk%3A6969&amp;tr=udp%3A%2F%2Fexodus.desync.com%3A6969","seeders":1,"leechers":1,"uploader":"rturner77","files":-1,"time":1409360955,"description":"Screens:\n &lt;a href=&quot;\nhttp://bayimg.com/laaIkaaGb&quot; rel=&quot;nofollow&quot; target=&quot;_NEW&quot;&gt;\nhttp://bayimg.com/laaIkaaGb&lt;/a&gt;","torrent":{"xt":"urn:btih:0711c6896c3a93f19b4436fc4c465decdae644b8","amp;dn":"FuckinVan.14.08.26.Lucia.Dinamita.Shes.Pure.Dynamite.XXX.SD.MP4-","amp;tr":["udp%3A%2F%2Ftracker.openbittorrent.com%3A80","udp%3A%2F%2Fopen.demonii.com%3A1337","udp%3A%2F%2Ftracker.coppersurfer.tk%3A6969","udp%3A%2F%2Fexodus.desync.com%3A6969"],"infoHash":"0711c6896c3a93f19b4436fc4c465decdae644b8","infoHashBuffer":{"type":"Buffer","data":[7,17,198,137,108,58,147,241,155,68,54,252,76,70,93,236,218,230,68,184]},"announce":[],"urlList":[]}}