{"title":"Globalization of Mobile and Wireless Communications: Today and i","uid":7651696,"size":29111105,"categoryP":"other","categoryS":"e_books","magnet":"?xt=urn:btih:14a933708669e78c60cc3562fd4c37b0b1a6e89a&amp;dn=Globalization+of+Mobile+and+Wireless+Communications%3A+Today+and+i&amp;tr=udp%3A%2F%2Ftracker.openbittorrent.com%3A80&amp;tr=udp%3A%2F%2Fopen.demonii.com%3A1337&amp;tr=udp%3A%2F%2Ftracker.coppersurfer.tk%3A6969&amp;tr=udp%3A%2F%2Fexodus.desync.com%3A6969","seeders":1,"leechers":0,"uploader":null,"files":-1,"time":1348043986,"description":" &lt;a href=&quot;http://lib.myilibrary.com.ezproxy1.lib.asu.edu/Open.aspx?id=299661&amp;loc=185&quot; rel=&quot;nofollow&quot; target=&quot;_NEW&quot;&gt;http://lib.myilibrary.com.ezproxy1.lib.asu.edu/Open.aspx?id=299661&amp;loc=185&lt;/a&gt;\nGlobalization of mobile and wireless communications: today and in 2020\nSearch ASU libraries for it\n\nGlobalization of Mobile and Wireless Communications: Today and in 2020 ISBN 9400701063 by Dixit and Ojanpera\n\nGlobalization of mobile and wireless communications today and in 2020\n\nE-Book\n\nProduct Details\nHardcover: 321 pages\nPublisher: Springer; 1st Edition. edition (December 2, 2010)\nLanguage: English\nISBN-10: 9400701063\nISBN-13: 978-9400701069\nProduct Dimensions: 9.3 x 6.2 x 1 inches\nShipping Weight: 1.5 pounds \n\nRetail price as of Sept 18, 2012:  $129.00 USD\nUsed price as of Sept 18, 2012:  Over $100 USD\n","torrent":{"xt":"urn:btih:14a933708669e78c60cc3562fd4c37b0b1a6e89a","amp;dn":"Globalization+of+Mobile+and+Wireless+Communications%3A+Today+and+i","amp;tr":["udp%3A%2F%2Ftracker.openbittorrent.com%3A80","udp%3A%2F%2Fopen.demonii.com%3A1337","udp%3A%2F%2Ftracker.coppersurfer.tk%3A6969","udp%3A%2F%2Fexodus.desync.com%3A6969"],"infoHash":"14a933708669e78c60cc3562fd4c37b0b1a6e89a","infoHashBuffer":{"type":"Buffer","data":[20,169,51,112,134,105,231,140,96,204,53,98,253,76,55,176,177,166,232,154]},"announce":[],"urlList":[]}}