{"title":"Hot Chocolate - Brother Louie - [TFM]","uid":7541876,"size":320604763,"categoryP":"audio","categoryS":"flac","magnet":"?xt=urn:btih:179e958b384e9e1b057cce29486d2d43f5b7a650&amp;dn=Hot+Chocolate+-+Brother+Louie+-+%5BTFM%5D&amp;tr=udp%3A%2F%2Ftracker.openbittorrent.com%3A80&amp;tr=udp%3A%2F%2Fopen.demonii.com%3A1337&amp;tr=udp%3A%2F%2Ftracker.coppersurfer.tk%3A6969&amp;tr=udp%3A%2F%2Fexodus.desync.com%3A6969","seeders":1,"leechers":0,"uploader":"tifon","files":-1,"time":1345237356,"description":"---------------------------------------------------------------------\n                    Hot Chocolate - Brother Louie\n---------------------------------------------------------------------\n\nArtist...............: Hot Chocolate\nAlbum................: Brother Louie\nGenre................: Pop/Rock\nSource...............: CD\nYear.................: 2002\nRipper...............: EAC (Secure mode) / LAME 3.92 &amp; Samsung CDRW/DVD SH-S202J\nCodec................: Free Lossless Audio Codec (FLAC)\nVersion..............: reference libFLAC 1.2.0 20070715\nQuality..............: Lossless, (avg. compression: 57 %)\nChannels.............: Stereo / 44100 HZ / 16 Bit\nTags.................: VorbisComment\nInformation..........: \n\nRipped by............: [TFM] on 2012.08.17.\nPosted by............: [TFM] on 2012.08.17.\nNews Server..........: \nNews Group(s)........: \n\nIncluded.............: NFO, SFV, M3U, CUE.\nCovers...............: Front Back CD LOG 2X\n\n---------------------------------------------------------------------\n                       Tracklisting\n---------------------------------------------------------------------\n\n   1. Hot Chocolate - Brother Louie                           [05:00]\n   2. Hot Chocolate - Cicero Park                             [04:42]\n   3. Hot Chocolate - Mindless Boogie                         [04:19]\n   4. Hot Chocolate - Could Have Been Born In The Getto       [05:50]\n   5. Hot Chocolate - Bump And Dilly Down                     [02:59]\n   6. Hot Chocolate - Chances                                 [04:00]\n   7. Hot Chocolate - Dance (Get Down On It)                  [04:43]\n   8. Hot Chocolate - Funky Rock 'N Roll                      [04:49]\n   9. Hot Chocolate - Sexy Carribean Girl                     [05:23]\n  10. Hot Chocolate - You're a Natural High                   [03:08]\n  11. Hot Chocolate - Harry                                   [04:00]\n  12. Hot Chocolate - A Child's Prayer                        [03:51]\n\nPlaying Time.........: 52:50\nTotal Size...........: 305,38 MB","torrent":{"xt":"urn:btih:179e958b384e9e1b057cce29486d2d43f5b7a650","amp;dn":"Hot+Chocolate+-+Brother+Louie+-+%5BTFM%5D","amp;tr":["udp%3A%2F%2Ftracker.openbittorrent.com%3A80","udp%3A%2F%2Fopen.demonii.com%3A1337","udp%3A%2F%2Ftracker.coppersurfer.tk%3A6969","udp%3A%2F%2Fexodus.desync.com%3A6969"],"infoHash":"179e958b384e9e1b057cce29486d2d43f5b7a650","infoHashBuffer":{"type":"Buffer","data":[23,158,149,139,56,78,158,27,5,124,206,41,72,109,45,67,245,183,166,80]},"announce":[],"urlList":[]}}