{"title":"Chriz Loud - Summer Night EP 2012","uid":7171702,"size":37892219,"categoryP":"audio","categoryS":"music","magnet":"?xt=urn:btih:1a5e88b1c2d95bd074944e72af281c42df3c8702&amp;dn=Chriz+Loud+-+Summer+Night+EP+2012&amp;tr=udp%3A%2F%2Ftracker.openbittorrent.com%3A80&amp;tr=udp%3A%2F%2Fopen.demonii.com%3A1337&amp;tr=udp%3A%2F%2Ftracker.coppersurfer.tk%3A6969&amp;tr=udp%3A%2F%2Fexodus.desync.com%3A6969","seeders":1,"leechers":0,"uploader":"ChrizLoud","files":-1,"time":1333986060,"description":"DATE    :   2012-04-09\nARTIST  :   Chriz Loud\nTITLE   :   Summer Night\nGENRE   :   House\nLABEL   :   Unsigned Artist\nURL     :  \nQUALITY :   320kbps CBR / Joint Stereo\nSOURCE  :   Single (EP)\nTRACKS  :   3\n\nDisc 1/1\n_______\n01 Chriz Loud - Summer Night (Radio Edit)               3:56\n02 Chriz Loud - Summer Night (Club Mix)                 5:55\n03 Chriz Loud - Summer Night (Club Mix Instrumental)    5:53\n____________________________________________________________________________________\n\n\nArtist info:\n\n&quot;Chriz Loud&quot; is a Swedish House music producer formerly known as &quot;deejaywasp&quot; with over 15 years\nof experience in writing his own music and remixing songs by other artists.\n\nThis is the new fresh artist name that he will be using from 2012 and on.\n","torrent":{"xt":"urn:btih:1a5e88b1c2d95bd074944e72af281c42df3c8702","amp;dn":"Chriz+Loud+-+Summer+Night+EP+2012","amp;tr":["udp%3A%2F%2Ftracker.openbittorrent.com%3A80","udp%3A%2F%2Fopen.demonii.com%3A1337","udp%3A%2F%2Ftracker.coppersurfer.tk%3A6969","udp%3A%2F%2Fexodus.desync.com%3A6969"],"infoHash":"1a5e88b1c2d95bd074944e72af281c42df3c8702","infoHashBuffer":{"type":"Buffer","data":[26,94,136,177,194,217,91,208,116,148,78,114,175,40,28,66,223,60,135,2]},"announce":[],"urlList":[]}}