{"title":"[StreetBlowjobs] Darcie Belle (Dick For Darcie / 06.07.2015)","uid":11996021,"size":429263874,"categoryP":"porn","categoryS":"movies","magnet":"?xt=urn:btih:20ff1c6a0e65f7c30b0deef22bf0c6d2f1d594fc&amp;dn=%5BStreetBlowjobs%5D+Darcie+Belle+%28Dick+For+Darcie+%2F+06.07.2015%29&amp;tr=udp%3A%2F%2Ftracker.openbittorrent.com%3A80&amp;tr=udp%3A%2F%2Fopen.demonii.com%3A1337&amp;tr=udp%3A%2F%2Ftracker.coppersurfer.tk%3A6969&amp;tr=udp%3A%2F%2Fexodus.desync.com%3A6969","seeders":1,"leechers":3,"uploader":"chkm8te","files":1,"time":1433657913,"description":"[StreetBlowjobs] Darcie Belle (Dick For Darcie / 06.07.2015)\n\nI spotted a hot blonde at a local park near my apartment last week. I noticed her there before, so I stopped by to see what was up. Turned out she was an art student working on one of her portraits. I got to talking with her and, like all students, Darcie was broke and in need of money. I offered to pay her for a portrait of myself, and she was into the idea. I told her I wanted it to be nude, but she wasn't feeling that until I offered her a whole lot more cash. We went back to my place, and I got naked. Darcie started doing my portrait, and I began getting hard. Of course, she noticed right away. It took some more money, but I soon had her naked feeling up my cock. I managed to get her wet enough to want to go all the way. You can't miss this girl and her perfect bubble butt bouncing all over my cock. She got the full facial dripping down to her perky tits at the end and loved it all, super hot stuff!\n\nScreens: &lt;a href=&quot;\nhttp://xxxhost.me/viewer.php?file=00tw5tin5hh8ep7x6jkc.jpg&quot; rel=&quot;nofollow&quot; target=&quot;_NEW&quot;&gt;\nhttp://xxxhost.me/viewer.php?file=00tw5tin5hh8ep7x6jkc.jpg&lt;/a&gt;\n &lt;a href=&quot;\nhttp://xxxhost.me/viewer.php?file=ghr0r87cxrtjo54z4ps2.jpg&quot; rel=&quot;nofollow&quot; target=&quot;_NEW&quot;&gt;\nhttp://xxxhost.me/viewer.php?file=ghr0r87cxrtjo54z4ps2.jpg&lt;/a&gt;","torrent":{"xt":"urn:btih:20ff1c6a0e65f7c30b0deef22bf0c6d2f1d594fc","amp;dn":"%5BStreetBlowjobs%5D+Darcie+Belle+%28Dick+For+Darcie+%2F+06.07.2015%29","amp;tr":["udp%3A%2F%2Ftracker.openbittorrent.com%3A80","udp%3A%2F%2Fopen.demonii.com%3A1337","udp%3A%2F%2Ftracker.coppersurfer.tk%3A6969","udp%3A%2F%2Fexodus.desync.com%3A6969"],"infoHash":"20ff1c6a0e65f7c30b0deef22bf0c6d2f1d594fc","infoHashBuffer":{"type":"Buffer","data":[32,255,28,106,14,101,247,195,11,13,238,242,43,240,198,210,241,213,148,252]},"announce":[],"urlList":[]}}