{"title":"Jimmy.Kimmel.2014.03.03.Rob.Ford.720p.HDTV.x264-BATV[rartv]","uid":9695348,"size":1444583557,"categoryP":"video","categoryS":"hd___tv_shows","magnet":"?xt=urn:btih:2ca3839a0261deaff1221015829e3caf463eb686&amp;dn=Jimmy.Kimmel.2014.03.03.Rob.Ford.720p.HDTV.x264-BATV%5Brartv%5D&amp;tr=udp%3A%2F%2Ftracker.openbittorrent.com%3A80&amp;tr=udp%3A%2F%2Fopen.demonii.com%3A1337&amp;tr=udp%3A%2F%2Ftracker.coppersurfer.tk%3A6969&amp;tr=udp%3A%2F%2Fexodus.desync.com%3A6969","seeders":1,"leechers":0,"uploader":"Drarbg","files":4,"time":1393926135,"description":"Jimmy.Kimmel.2014.03.03.Rob.Ford.720p.HDTV.x264-BATV[rartv]\n-----------------------------------------\nScreens : &lt;a href=&quot;\nhttp://imagecurl.org/viewer.php?file=23466308198919938788.jpg&quot; rel=&quot;nofollow&quot; target=&quot;_NEW&quot;&gt;\nhttp://imagecurl.org/viewer.php?file=23466308198919938788.jpg&lt;/a&gt;\n\n","torrent":{"xt":"urn:btih:2ca3839a0261deaff1221015829e3caf463eb686","amp;dn":"Jimmy.Kimmel.2014.03.03.Rob.Ford.720p.HDTV.x264-BATV%5Brartv%5D","amp;tr":["udp%3A%2F%2Ftracker.openbittorrent.com%3A80","udp%3A%2F%2Fopen.demonii.com%3A1337","udp%3A%2F%2Ftracker.coppersurfer.tk%3A6969","udp%3A%2F%2Fexodus.desync.com%3A6969"],"infoHash":"2ca3839a0261deaff1221015829e3caf463eb686","infoHashBuffer":{"type":"Buffer","data":[44,163,131,154,2,97,222,175,241,34,16,21,130,158,60,175,70,62,182,134]},"announce":[],"urlList":[]}}