{"title":"Sugababes - Sweet 7 (Album Sampler Featuring Keisha Buchanan)","uid":5138286,"size":52560235,"categoryP":"audio","categoryS":"music","magnet":"?xt=urn:btih:2e39b3f70729c03614b49afe05414504c87a8877&amp;dn=Sugababes+-+Sweet+7+%28Album+Sampler+Featuring+Keisha+Buchanan%29&amp;tr=udp%3A%2F%2Ftracker.openbittorrent.com%3A80&amp;tr=udp%3A%2F%2Fopen.demonii.com%3A1337&amp;tr=udp%3A%2F%2Ftracker.coppersurfer.tk%3A6969&amp;tr=udp%3A%2F%2Fexodus.desync.com%3A6969","seeders":1,"leechers":0,"uploader":null,"files":-1,"time":1256676921,"description":"Sugababes - Sweet 7\n\n6 Track album sampler.\n\nFeaturing Keisha Buchanan on Vocals.\n\ntracks:\n\n1. Get Sexy (Original Version)\n\n2. About A Girl (Original Version)\n\n3. Miss Everything (Featuring Sean Kingston) (Original Version)\n\n4. Wear My Kiss (Original Version)\n\n5. Wait For You (Original Version)\n\n6. Thank You For The Heartbreak (Original Version)\n\n\nEnjoy and please re-seed.","torrent":{"xt":"urn:btih:2e39b3f70729c03614b49afe05414504c87a8877","amp;dn":"Sugababes+-+Sweet+7+%28Album+Sampler+Featuring+Keisha+Buchanan%29","amp;tr":["udp%3A%2F%2Ftracker.openbittorrent.com%3A80","udp%3A%2F%2Fopen.demonii.com%3A1337","udp%3A%2F%2Ftracker.coppersurfer.tk%3A6969","udp%3A%2F%2Fexodus.desync.com%3A6969"],"infoHash":"2e39b3f70729c03614b49afe05414504c87a8877","infoHashBuffer":{"type":"Buffer","data":[46,57,179,247,7,41,192,54,20,180,154,254,5,65,69,4,200,122,136,119]},"announce":[],"urlList":[]}}