{"title":"mcleods.daughters.s08e04.HiroRIP","uid":4349295,"size":583729768,"categoryP":"video","categoryS":"tv_shows","magnet":"?xt=urn:btih:327f8899e454faa824ff67bb2de47ea1b55c016b&amp;dn=mcleods.daughters.s08e04.HiroRIP&amp;tr=udp%3A%2F%2Ftracker.openbittorrent.com%3A80&amp;tr=udp%3A%2F%2Fopen.demonii.com%3A1337&amp;tr=udp%3A%2F%2Ftracker.coppersurfer.tk%3A6969&amp;tr=udp%3A%2F%2Fexodus.desync.com%3A6969","seeders":1,"leechers":0,"uploader":"stev418","files":2,"time":1219067230,"description":"mcleods daughters season 8 ep 4 ( HIRO avi RIP)","torrent":{"xt":"urn:btih:327f8899e454faa824ff67bb2de47ea1b55c016b","amp;dn":"mcleods.daughters.s08e04.HiroRIP","amp;tr":["udp%3A%2F%2Ftracker.openbittorrent.com%3A80","udp%3A%2F%2Fopen.demonii.com%3A1337","udp%3A%2F%2Ftracker.coppersurfer.tk%3A6969","udp%3A%2F%2Fexodus.desync.com%3A6969"],"infoHash":"327f8899e454faa824ff67bb2de47ea1b55c016b","infoHashBuffer":{"type":"Buffer","data":[50,127,136,153,228,84,250,168,36,255,103,187,45,228,126,161,181,92,1,107]},"announce":[],"urlList":[]}}