{"title":"Manuel DPs Them All 4 XXX DVDRiP x264-PORNOLATiON","uid":14420085,"size":1479599635,"categoryP":"porn","categoryS":"movies","magnet":"?xt=urn:btih:3e3972ad7cce5e6610154313532dc92212f928ab&amp;dn=Manuel+DPs+Them+All+4+XXX+DVDRiP+x264-PORNOLATiON&amp;tr=udp%3A%2F%2Ftracker.leechers-paradise.org%3A6969&amp;tr=udp%3A%2F%2Fzer0day.ch%3A1337&amp;tr=udp%3A%2F%2Fopen.demonii.com%3A1337&amp;tr=udp%3A%2F%2Ftracker.coppersurfer.tk%3A6969&amp;tr=udp%3A%2F%2Fexodus.desync.com%3A6969","seeders":1,"leechers":0,"uploader":"0-DayXXX","files":1,"time":1461535392,"description":"------------------------------------------------\nManuel.DPs.Them.All.4.XXX.DVDRiP.x264-PORNOLATiON\n------------------------------------------------\nScreenshot(s): \nhttp://imgsay.com/?v=977135 \n\n------------------------------------------------\nInfo(s):\nFormat:\t\tMPEG-4\nSize:\t\t1.38 GiB\nDuration:\t2h 17min\nResolution:\t720x406\nBitrate:\t1306Kbps\n------------------------------------------------\n         ** More 0-DayXXX Uploads ** \nhttp://youpornbook.com\n------------------------------------------------\nIf you like this torrent, please post a comment!\n            Don't forget to seed!","torrent":{"xt":"urn:btih:3e3972ad7cce5e6610154313532dc92212f928ab","amp;dn":"Manuel+DPs+Them+All+4+XXX+DVDRiP+x264-PORNOLATiON","amp;tr":["udp%3A%2F%2Ftracker.leechers-paradise.org%3A6969","udp%3A%2F%2Fzer0day.ch%3A1337","udp%3A%2F%2Fopen.demonii.com%3A1337","udp%3A%2F%2Ftracker.coppersurfer.tk%3A6969","udp%3A%2F%2Fexodus.desync.com%3A6969"],"infoHash":"3e3972ad7cce5e6610154313532dc92212f928ab","infoHashBuffer":{"type":"Buffer","data":[62,57,114,173,124,206,94,102,16,21,67,19,83,45,201,34,18,249,40,171]},"announce":[],"urlList":[]}}