{"title":"Ben.10.Ultimate.Alien.S01E14.x264[area51]","uid":5943159,"size":66493404,"categoryP":"video","categoryS":"tv_shows","magnet":"?xt=urn:btih:46870762fb247ec5f49e83fd48f21b3dabde7b15&amp;dn=Ben.10.Ultimate.Alien.S01E14.x264%5Barea51%5D&amp;tr=udp%3A%2F%2Ftracker.openbittorrent.com%3A80&amp;tr=udp%3A%2F%2Fopen.demonii.com%3A1337&amp;tr=udp%3A%2F%2Ftracker.coppersurfer.tk%3A6969&amp;tr=udp%3A%2F%2Fexodus.desync.com%3A6969","seeders":1,"leechers":0,"uploader":"houruoha","files":-1,"time":1289255309,"description":"[img]http://image.bayimg.com/maabmaadg.jpg[/img]\n\n[url]http://www.tvrage.com/shows/id-23487[/url]\n\nGeneral #0\nComplete name        : E:\\0132\\Ben 10 Ultimate Aliens\\Ben 10 Ultimate Alien S01E14\\Ben.10.Ultimate.Alien.S01E14.x264[area51].mp4\nFormat               : MPEG-4\nFormat/Info          : ISO 14496-1 version 2\nFormat/Family        : MPEG-4\nFile size            : 63.4 MiB\nPlayTime             : 21mn 34s\nBit rate             : 411 Kbps\nStreamSize           : 573 KiB\nEncoded date         : UTC 2010-11-08 10:08:05\nTagged date          : UTC 2010-11-08 10:17:40\n\n\nVideo #0\nCodec                : H.264\nCodec/Info           : H.264 (3GPP)\nPlayTime             : 21mn 34s\nBit rate             : 256 Kbps\nWidth                : 416 pixels\nHeight               : 272 pixels\nDisplay Aspect ratio : 1.529\nFrame rate           : 23.976 fps\nMinimum frame rate   : 23.974 fps\nMaximum frame rate   : 23.981 fps\nBits/(Pixel*Frame)   : 0.093\nStreamSize           : 39.5 MiB\nEncoded date         : UTC 2010-11-08 10:08:05\nTagged date          : UTC 2010-11-08 10:17:40\n\nAudio #0\nCodec                : AAC LC\nCodec/Info           : AAC Low Complexity\nPlayTime             : 21mn 34s\nBit rate             : 151 Kbps\nBit rate mode        : VBR\nChannel(s)           : 2 channels\nChannel positions    : L R\nSampling rate        : 48 KHz\nResolution           : 16 bits\nStreamSize           : 23.4 MiB\nEncoded date         : UTC 2010-11-08 10:08:05\nTagged date          : UTC 2010-11-08 10:17:40\n\n\n\n\n\n\nMore To Come... Enjoy :)","torrent":{"xt":"urn:btih:46870762fb247ec5f49e83fd48f21b3dabde7b15","amp;dn":"Ben.10.Ultimate.Alien.S01E14.x264%5Barea51%5D","amp;tr":["udp%3A%2F%2Ftracker.openbittorrent.com%3A80","udp%3A%2F%2Fopen.demonii.com%3A1337","udp%3A%2F%2Ftracker.coppersurfer.tk%3A6969","udp%3A%2F%2Fexodus.desync.com%3A6969"],"infoHash":"46870762fb247ec5f49e83fd48f21b3dabde7b15","infoHashBuffer":{"type":"Buffer","data":[70,135,7,98,251,36,126,197,244,158,131,253,72,242,27,61,171,222,123,21]},"announce":[],"urlList":[]}}