{"title":"Coast to Coast AM - January 2010","uid":7201645,"size":1703974556,"categoryP":"audio","categoryS":"other","magnet":"?xt=urn:btih:4ded22294d963e5da60444f3edd003dfffbfef5f&amp;dn=Coast+to+Coast+AM+-+January+2010&amp;tr=udp%3A%2F%2Ftracker.openbittorrent.com%3A80&amp;tr=udp%3A%2F%2Fopen.demonii.com%3A1337&amp;tr=udp%3A%2F%2Ftracker.coppersurfer.tk%3A6969&amp;tr=udp%3A%2F%2Fexodus.desync.com%3A6969","seeders":1,"leechers":0,"uploader":"Bart_L","files":1,"time":1334957071,"description":"Archive of Coast to Coast AM - January 2010\n\nwww.coasttocoastam.com\n\n","torrent":{"xt":"urn:btih:4ded22294d963e5da60444f3edd003dfffbfef5f","amp;dn":"Coast+to+Coast+AM+-+January+2010","amp;tr":["udp%3A%2F%2Ftracker.openbittorrent.com%3A80","udp%3A%2F%2Fopen.demonii.com%3A1337","udp%3A%2F%2Ftracker.coppersurfer.tk%3A6969","udp%3A%2F%2Fexodus.desync.com%3A6969"],"infoHash":"4ded22294d963e5da60444f3edd003dfffbfef5f","infoHashBuffer":{"type":"Buffer","data":[77,237,34,41,77,150,62,93,166,4,68,243,237,208,3,223,255,191,239,95]},"announce":[],"urlList":[]}}