{"title":"300 (2007) Blu-ray CEE 1080p VC-1 TrueHD 5.1- HDmonSK","uid":8279411,"size":31752274452,"categoryP":"video","categoryS":"hd___movies","magnet":"?xt=urn:btih:4e3cadc3659fe8433fffe18224d22c59ae347e25&amp;dn=300+%282007%29+Blu-ray+CEE+1080p+VC-1+TrueHD+5.1-+HDmonSK&amp;tr=udp%3A%2F%2Ftracker.openbittorrent.com%3A80&amp;tr=udp%3A%2F%2Fopen.demonii.com%3A1337&amp;tr=udp%3A%2F%2Ftracker.coppersurfer.tk%3A6969&amp;tr=udp%3A%2F%2Fexodus.desync.com%3A6969","seeders":1,"leechers":0,"uploader":"HighCode","files":175,"time":1363798114,"description":"&quot;300 (2007) Blu-ray CEE 1080p VC-1 DD5.1-HDmonSK&quot; is release title,\nbut DD5.1 is not right because ENG is the default track for us.\n &lt;a href=&quot;\nhttp://www.imdb.com/title/tt0416449/&quot; rel=&quot;nofollow&quot; target=&quot;_NEW&quot;&gt;\nhttp://www.imdb.com/title/tt0416449/&lt;/a&gt;\n\nDISC INFO:\nDisc Title:     300\nDisc Size:      31 752 274 452 bytes\nProtection:     AACS\nBD-Java:        No\nPLAYLIST REPORT:\nName:                   00004.MPLS\nSize:                   45 874 368 bytes\nLength:                 1:56:38 (h:m:s)\nTotal Bitrate:          0,05 Mbps\nDescription:\nVIDEO:\nCodec                   Bitrate             Description\n-----                   -------             -----------\nVC-1 Video              14686 kbps          1080p / 23,976 fps / 16:9 / Advanced Profile 3\nAUDIO:\nCodec                           Language        Bitrate         Description\n-----                           --------        -------         -----------\nDolby TrueHD Audio              English         1594 kbps       5.1 / 48 kHz / 1594 kbps / 16-bit (AC3 Core: 5.1 / 48 kHz / 640 kbps)\nDolby Digital Audio             English         640 kbps        5.1 / 48 kHz / 640 kbps\nDolby Digital Audio             Czech           448 kbps        5.1 / 48 kHz / 448 kbps\nDolby Digital Audio             Hungarian       448 kbps        5.1 / 48 kHz / 448 kbps\nDolby Digital Audio             Polish          448 kbps        5.1 / 48 kHz / 448 kbps\nDolby Digital Audio             Portuguese      448 kbps        5.1 / 48 kHz / 448 kbps\nDolby Digital Audio             Russian         448 kbps        5.1 / 48 kHz / 448 kbps\nDolby Digital Audio             Thai            448 kbps        5.1 / 48 kHz / 448 kbps\nDolby Digital Audio             Turkish         448 kbps        5.1 / 48 kHz / 448 kbps\nDolby Digital Audio             English         192 kbps        2.0 / 48 kHz / 192 kbps / Dolby Surround\n\nSUBTITLES (PG-s):  English + SDH, Arabic, Bulgarian, Chinese (Mandarin), Croatian, Czech, Estonian, French, Greek, Hebrew, Hungarian, Icelandic, Indonesian, Korean, Latvian, Lithuanian, Polish, Portuguese (Brazilian), Romanian, Russian, Serbian, Slovenian, Spanish (Latin American), Thai, Turkish, Ukrainian","torrent":{"xt":"urn:btih:4e3cadc3659fe8433fffe18224d22c59ae347e25","amp;dn":"300+%282007%29+Blu-ray+CEE+1080p+VC-1+TrueHD+5.1-+HDmonSK","amp;tr":["udp%3A%2F%2Ftracker.openbittorrent.com%3A80","udp%3A%2F%2Fopen.demonii.com%3A1337","udp%3A%2F%2Ftracker.coppersurfer.tk%3A6969","udp%3A%2F%2Fexodus.desync.com%3A6969"],"infoHash":"4e3cadc3659fe8433fffe18224d22c59ae347e25","infoHashBuffer":{"type":"Buffer","data":[78,60,173,195,101,159,232,67,63,255,225,130,36,210,44,89,174,52,126,37]},"announce":[],"urlList":[]}}