{"title":"[GirlyRiders] - Paige Turnah - [Creampie The Girly Rider]","uid":8666483,"size":222345116,"categoryP":"porn","categoryS":"other","magnet":"?xt=urn:btih:58a0bcfd6dfcab40063097bf72a819b9cbef026e&amp;dn=%5BGirlyRiders%5D+-+Paige+Turnah+-+%5BCreampie+The+Girly+Rider%5D&amp;tr=udp%3A%2F%2Ftracker.openbittorrent.com%3A80&amp;tr=udp%3A%2F%2Fopen.demonii.com%3A1337&amp;tr=udp%3A%2F%2Ftracker.coppersurfer.tk%3A6969&amp;tr=udp%3A%2F%2Fexodus.desync.com%3A6969","seeders":1,"leechers":0,"uploader":"R0thschild","files":2,"time":1373412023,"description":"              ***********************************************\n\n                PublicHash - Largest Bittorrent Community\n      \n                         &lt;a href=&quot; http://publichash.com/&quot; rel=&quot;nofollow&quot; target=&quot;_NEW&quot;&gt; http://publichash.com/&lt;/a&gt;\n\n          Crystal Clean files - Fast Speed! No Virus! No Fake! Enjoy!\n    \n              ***********************************************\n\nGallery: &lt;a href=&quot;\nhttp://imgsure.com/?v=795013&quot; rel=&quot;nofollow&quot; target=&quot;_NEW&quot;&gt;\nhttp://imgsure.com/?v=795013&lt;/a&gt;","torrent":{"xt":"urn:btih:58a0bcfd6dfcab40063097bf72a819b9cbef026e","amp;dn":"%5BGirlyRiders%5D+-+Paige+Turnah+-+%5BCreampie+The+Girly+Rider%5D","amp;tr":["udp%3A%2F%2Ftracker.openbittorrent.com%3A80","udp%3A%2F%2Fopen.demonii.com%3A1337","udp%3A%2F%2Ftracker.coppersurfer.tk%3A6969","udp%3A%2F%2Fexodus.desync.com%3A6969"],"infoHash":"58a0bcfd6dfcab40063097bf72a819b9cbef026e","infoHashBuffer":{"type":"Buffer","data":[88,160,188,253,109,252,171,64,6,48,151,191,114,168,25,185,203,239,2,110]},"announce":[],"urlList":[]}}