{"title":"Shemale XTC 01 - Carmen Cruz &amp; Vo D'Balm.avi","uid":7997046,"size":267143360,"categoryP":"porn","categoryS":"movie_clips","magnet":"?xt=urn:btih:6a9f9db2df0d682daae4f5fd6df70cb4a3005afc&amp;dn=Shemale+XTC+01+-+Carmen+Cruz+%26amp%3B+Vo+D%27Balm.avi&amp;tr=udp%3A%2F%2Ftracker.openbittorrent.com%3A80&amp;tr=udp%3A%2F%2Fopen.demonii.com%3A1337&amp;tr=udp%3A%2F%2Ftracker.coppersurfer.tk%3A6969&amp;tr=udp%3A%2F%2Fexodus.desync.com%3A6969","seeders":1,"leechers":0,"uploader":"ibxxxxxxxxxx","files":1,"time":1357606151,"description":"Shemale XTC 01 - Carmen Cruz &amp; Vo D'Balm.avi\n\nHot Shemale Action\n\nReleased: 2007\n24 Minutes\n720 x 576\n\nMessage Me if the File Needs to be Re-Seeded\n\nPlease Keep Seeding after Download\n\nStarring\n\nCarmen Cruz &lt;a href=&quot;\nhttp://postimage.org/image/vbakc9gql/&quot; rel=&quot;nofollow&quot; target=&quot;_NEW&quot;&gt;\nhttp://postimage.org/image/vbakc9gql/&lt;/a&gt;\n\nVo D'Balm &lt;a href=&quot;\nhttp://postimage.org/image/51kwfq5fh/&quot; rel=&quot;nofollow&quot; target=&quot;_NEW&quot;&gt;\nhttp://postimage.org/image/51kwfq5fh/&lt;/a&gt;\n\n\nScreenshots &lt;a href=&quot;\nhttp://postimage.org/image/ne8v9eo71/&quot; rel=&quot;nofollow&quot; target=&quot;_NEW&quot;&gt;\nhttp://postimage.org/image/ne8v9eo71/&lt;/a&gt;\n","torrent":{"xt":"urn:btih:6a9f9db2df0d682daae4f5fd6df70cb4a3005afc","amp;dn":"Shemale+XTC+01+-+Carmen+Cruz+%26amp%3B+Vo+D%27Balm.avi","amp;tr":["udp%3A%2F%2Ftracker.openbittorrent.com%3A80","udp%3A%2F%2Fopen.demonii.com%3A1337","udp%3A%2F%2Ftracker.coppersurfer.tk%3A6969","udp%3A%2F%2Fexodus.desync.com%3A6969"],"infoHash":"6a9f9db2df0d682daae4f5fd6df70cb4a3005afc","infoHashBuffer":{"type":"Buffer","data":[106,159,157,178,223,13,104,45,170,228,245,253,109,247,12,180,163,0,90,252]},"announce":[],"urlList":[]}}