{"title":"Eagle Eye ITALIAN 2009-BY NERO69.avi","uid":4705651,"size":569633598,"categoryP":"video","categoryS":"movies","magnet":"?xt=urn:btih:707b641f333394b37dab701cdcd6c9db3896fbc2&amp;dn=Eagle+Eye+ITALIAN+2009-BY+NERO69.avi&amp;tr=udp%3A%2F%2Ftracker.openbittorrent.com%3A80&amp;tr=udp%3A%2F%2Fopen.demonii.com%3A1337&amp;tr=udp%3A%2F%2Ftracker.coppersurfer.tk%3A6969&amp;tr=udp%3A%2F%2Fexodus.desync.com%3A6969","seeders":1,"leechers":0,"uploader":"NERINO69","files":1,"time":1233853232,"description":"eagle eye ita","torrent":{"xt":"urn:btih:707b641f333394b37dab701cdcd6c9db3896fbc2","amp;dn":"Eagle+Eye+ITALIAN+2009-BY+NERO69.avi","amp;tr":["udp%3A%2F%2Ftracker.openbittorrent.com%3A80","udp%3A%2F%2Fopen.demonii.com%3A1337","udp%3A%2F%2Ftracker.coppersurfer.tk%3A6969","udp%3A%2F%2Fexodus.desync.com%3A6969"],"infoHash":"707b641f333394b37dab701cdcd6c9db3896fbc2","infoHashBuffer":{"type":"Buffer","data":[112,123,100,31,51,51,148,179,125,171,112,28,220,214,201,219,56,150,251,194]},"announce":[],"urlList":[]}}