{"title":"Jacked.S01E10.HDTV.x264-CROOKS","uid":10454897,"size":687511853,"categoryP":"video","categoryS":"tv_shows","magnet":"?xt=urn:btih:ab403af79b92560421dee5b4e1a28e7be8ae79ad&amp;dn=Jacked.S01E10.HDTV.x264-CROOKS&amp;tr=udp%3A%2F%2Ftracker.openbittorrent.com%3A80&amp;tr=udp%3A%2F%2Fopen.demonii.com%3A1337&amp;tr=udp%3A%2F%2Ftracker.coppersurfer.tk%3A6969&amp;tr=udp%3A%2F%2Fexodus.desync.com%3A6969","seeders":1,"leechers":0,"uploader":"TvTeam","files":5,"time":1404062436,"description":"::::::::::::::::::::::::::::::::::::::::::::::::::::::::::::::::::::::::::\n       &lt;a href=&quot;\nhttp://www.torrenting.com&quot; rel=&quot;nofollow&quot; target=&quot;_NEW&quot;&gt;\nhttp://www.torrenting.com&lt;/a&gt;\n\nFeel the speed. come and enjoy ;-)\n\n::::::::::::::::::::::::::::::::::::::::::::::::::::::::::::::::::::::::::","torrent":{"xt":"urn:btih:ab403af79b92560421dee5b4e1a28e7be8ae79ad","amp;dn":"Jacked.S01E10.HDTV.x264-CROOKS","amp;tr":["udp%3A%2F%2Ftracker.openbittorrent.com%3A80","udp%3A%2F%2Fopen.demonii.com%3A1337","udp%3A%2F%2Ftracker.coppersurfer.tk%3A6969","udp%3A%2F%2Fexodus.desync.com%3A6969"],"infoHash":"ab403af79b92560421dee5b4e1a28e7be8ae79ad","infoHashBuffer":{"type":"Buffer","data":[171,64,58,247,155,146,86,4,33,222,229,180,225,162,142,123,232,174,121,173]},"announce":[],"urlList":[]}}