{"title":"[TeenSexMania.com] Lindsey-20.11.2010","uid":5969777,"size":400143944,"categoryP":"porn","categoryS":"movies","magnet":"?xt=urn:btih:b0cdd8735c9bc0e06e8bef4330253ce5c1bb6849&amp;dn=%5BTeenSexMania.com%5D+Lindsey-20.11.2010&amp;tr=udp%3A%2F%2Ftracker.openbittorrent.com%3A80&amp;tr=udp%3A%2F%2Fopen.demonii.com%3A1337&amp;tr=udp%3A%2F%2Ftracker.coppersurfer.tk%3A6969&amp;tr=udp%3A%2F%2Fexodus.desync.com%3A6969","seeders":1,"leechers":0,"uploader":"exmnova","files":1,"time":1290244023,"description":"[TeenSexMania.com] Lindsey-20.11.2010\n\n &lt;a href=&quot; http://www.picswan.com/img/share.php?id=4AF2_4CE78206&quot; rel=&quot;nofollow&quot; target=&quot;_NEW&quot;&gt; http://www.picswan.com/img/share.php?id=4AF2_4CE78206&lt;/a&gt;\n\n &lt;a href=&quot; http://www.picswan.com/img/share.php?id=CF26_4CE78206&quot; rel=&quot;nofollow&quot; target=&quot;_NEW&quot;&gt; http://www.picswan.com/img/share.php?id=CF26_4CE78206&lt;/a&gt;\n\n","torrent":{"xt":"urn:btih:b0cdd8735c9bc0e06e8bef4330253ce5c1bb6849","amp;dn":"%5BTeenSexMania.com%5D+Lindsey-20.11.2010","amp;tr":["udp%3A%2F%2Ftracker.openbittorrent.com%3A80","udp%3A%2F%2Fopen.demonii.com%3A1337","udp%3A%2F%2Ftracker.coppersurfer.tk%3A6969","udp%3A%2F%2Fexodus.desync.com%3A6969"],"infoHash":"b0cdd8735c9bc0e06e8bef4330253ce5c1bb6849","infoHashBuffer":{"type":"Buffer","data":[176,205,216,115,92,155,192,224,110,139,239,67,48,37,60,229,193,187,104,73]},"announce":[],"urlList":[]}}