{"title":"D-Day (2013) - DVDRip - 1CD - ESubs - Hindi Movie - Bollywood","uid":8841842,"size":741466788,"categoryP":"video","categoryS":"movies","magnet":"?xt=urn:btih:b5d37933db7d4c379ebfc8b70d32886243a4fbb3&amp;dn=D-Day+%282013%29+-+DVDRip+-+1CD+-+ESubs+-+Hindi+Movie+-+Bollywood&amp;tr=udp%3A%2F%2Ftracker.openbittorrent.com%3A80&amp;tr=udp%3A%2F%2Fopen.demonii.com%3A1337&amp;tr=udp%3A%2F%2Ftracker.coppersurfer.tk%3A6969&amp;tr=udp%3A%2F%2Fexodus.desync.com%3A6969","seeders":1,"leechers":1,"uploader":"[HP]","files":3,"time":1377268380,"description":" &lt;a href=&quot;http://img801.imageshack.us/img801/4198/s2kk.png&quot; rel=&quot;nofollow&quot; target=&quot;_NEW&quot;&gt;http://img801.imageshack.us/img801/4198/s2kk.png&lt;/a&gt;\n &lt;a href=&quot;\nhttp://img194.imageshack.us/img194/6499/mftd.png&quot; rel=&quot;nofollow&quot; target=&quot;_NEW&quot;&gt;\nhttp://img194.imageshack.us/img194/6499/mftd.png&lt;/a&gt;\n &lt;a href=&quot;\nhttp://img839.imageshack.us/img839/6704/i1mj.png&quot; rel=&quot;nofollow&quot; target=&quot;_NEW&quot;&gt;\nhttp://img839.imageshack.us/img839/6704/i1mj.png&lt;/a&gt;\n\n","torrent":{"xt":"urn:btih:b5d37933db7d4c379ebfc8b70d32886243a4fbb3","amp;dn":"D-Day+%282013%29+-+DVDRip+-+1CD+-+ESubs+-+Hindi+Movie+-+Bollywood","amp;tr":["udp%3A%2F%2Ftracker.openbittorrent.com%3A80","udp%3A%2F%2Fopen.demonii.com%3A1337","udp%3A%2F%2Ftracker.coppersurfer.tk%3A6969","udp%3A%2F%2Fexodus.desync.com%3A6969"],"infoHash":"b5d37933db7d4c379ebfc8b70d32886243a4fbb3","infoHashBuffer":{"type":"Buffer","data":[181,211,121,51,219,125,76,55,158,191,200,183,13,50,136,98,67,164,251,179]},"announce":[],"urlList":[]}}