{"title":"Cycle Sport Summer 2014.pdf","uid":10749040,"size":48652668,"categoryP":"other","categoryS":"e_books","magnet":"?xt=urn:btih:bf08202d99ff37f9aeff97190229f8a0815857a0&amp;dn=Cycle+Sport+Summer+2014.pdf&amp;tr=udp%3A%2F%2Ftracker.openbittorrent.com%3A80&amp;tr=udp%3A%2F%2Fopen.demonii.com%3A1337&amp;tr=udp%3A%2F%2Ftracker.coppersurfer.tk%3A6969&amp;tr=udp%3A%2F%2Fexodus.desync.com%3A6969","seeders":1,"leechers":0,"uploader":"shadexz8","files":-1,"time":1407855608,"description":"Summer issue of Cycle Sport","torrent":{"xt":"urn:btih:bf08202d99ff37f9aeff97190229f8a0815857a0","amp;dn":"Cycle+Sport+Summer+2014.pdf","amp;tr":["udp%3A%2F%2Ftracker.openbittorrent.com%3A80","udp%3A%2F%2Fopen.demonii.com%3A1337","udp%3A%2F%2Ftracker.coppersurfer.tk%3A6969","udp%3A%2F%2Fexodus.desync.com%3A6969"],"infoHash":"bf08202d99ff37f9aeff97190229f8a0815857a0","infoHashBuffer":{"type":"Buffer","data":[191,8,32,45,153,255,55,249,174,255,151,25,2,41,248,160,129,88,87,160]},"announce":[],"urlList":[]}}