{"title":"Send Untraceable Emails to Anyone","uid":4732533,"size":2411,"categoryP":"other","categoryS":"other","magnet":"?xt=urn:btih:cac6b8c9c3e09e3c5ff94addd491f9219772fe5e&amp;dn=Send+Untraceable+Emails+to+Anyone&amp;tr=udp%3A%2F%2Ftracker.openbittorrent.com%3A80&amp;tr=udp%3A%2F%2Fopen.demonii.com%3A1337&amp;tr=udp%3A%2F%2Ftracker.coppersurfer.tk%3A6969&amp;tr=udp%3A%2F%2Fexodus.desync.com%3A6969","seeders":1,"leechers":1,"uploader":"gangsta1313","files":1,"time":1235107229,"description":"This is a simple txt. document I wrote on how-to send untraceable emails to anyone.Injoye.","torrent":{"xt":"urn:btih:cac6b8c9c3e09e3c5ff94addd491f9219772fe5e","amp;dn":"Send+Untraceable+Emails+to+Anyone","amp;tr":["udp%3A%2F%2Ftracker.openbittorrent.com%3A80","udp%3A%2F%2Fopen.demonii.com%3A1337","udp%3A%2F%2Ftracker.coppersurfer.tk%3A6969","udp%3A%2F%2Fexodus.desync.com%3A6969"],"infoHash":"cac6b8c9c3e09e3c5ff94addd491f9219772fe5e","infoHashBuffer":{"type":"Buffer","data":[202,198,184,201,195,224,158,60,95,249,74,221,212,145,249,33,151,114,254,94]},"announce":[],"urlList":[]}}