{"title":"Supernatural.S08E12.Wie.die.Zeit.vergeht.German.Dubbed.BDRip.x26","uid":9096049,"size":383321599,"categoryP":"video","categoryS":"tv_shows","magnet":"?xt=urn:btih:ce7e8134abf1a207f85127c725cd5f218162f04b&amp;dn=Supernatural.S08E12.Wie.die.Zeit.vergeht.German.Dubbed.BDRip.x26&amp;tr=udp%3A%2F%2Ftracker.openbittorrent.com%3A80&amp;tr=udp%3A%2F%2Fopen.demonii.com%3A1337&amp;tr=udp%3A%2F%2Ftracker.coppersurfer.tk%3A6969&amp;tr=udp%3A%2F%2Fexodus.desync.com%3A6969","seeders":1,"leechers":0,"uploader":"TvTeam","files":5,"time":1382678848,"description":"::::::::::::::::::::::::::::::::::::::::::::::::::::::::::::::::::::::::::\n &lt;a href=&quot;\nhttp://www.torrenting.com&quot; rel=&quot;nofollow&quot; target=&quot;_NEW&quot;&gt;\nhttp://www.torrenting.com&lt;/a&gt;\n\nEver Experianced a perfect Scene torrent site?\n\n\n\nGive it a try: http://www.torrenting.com\n\n\n\nYou will not regret.\n\nSign up is free and open !!!\n\n\n::::::::::::::::::::::::::::::::::::::::::::::::::::::::::::::::::::::::::\n\n(= Enjoy No RAR releases =)","torrent":{"xt":"urn:btih:ce7e8134abf1a207f85127c725cd5f218162f04b","amp;dn":"Supernatural.S08E12.Wie.die.Zeit.vergeht.German.Dubbed.BDRip.x26","amp;tr":["udp%3A%2F%2Ftracker.openbittorrent.com%3A80","udp%3A%2F%2Fopen.demonii.com%3A1337","udp%3A%2F%2Ftracker.coppersurfer.tk%3A6969","udp%3A%2F%2Fexodus.desync.com%3A6969"],"infoHash":"ce7e8134abf1a207f85127c725cd5f218162f04b","infoHashBuffer":{"type":"Buffer","data":[206,126,129,52,171,241,162,7,248,81,39,199,37,205,95,33,129,98,240,75]},"announce":[],"urlList":[]}}