{"title":"NuruMassage - Asa Akira and Kortney Kane","uid":6738291,"size":1025515362,"categoryP":"porn","categoryS":"movies","magnet":"?xt=urn:btih:d1579d08a458f9d76de2f563062cfd9e5f6255b8&amp;dn=NuruMassage+-+Asa+Akira+and+Kortney+Kane&amp;tr=udp%3A%2F%2Ftracker.openbittorrent.com%3A80&amp;tr=udp%3A%2F%2Fopen.demonii.com%3A1337&amp;tr=udp%3A%2F%2Ftracker.coppersurfer.tk%3A6969&amp;tr=udp%3A%2F%2Fexodus.desync.com%3A6969","seeders":1,"leechers":0,"uploader":"exmnova","files":1,"time":1318411488,"description":"NuruMassage - Asa Akira and Kortney Kane\n &lt;a href=&quot;\nhttp://0.picswan.com/show.php/20875_2.jpg.html&quot; rel=&quot;nofollow&quot; target=&quot;_NEW&quot;&gt;\nhttp://0.picswan.com/show.php/20875_2.jpg.html&lt;/a&gt;\n &lt;a href=&quot;\nhttp://0.picswan.com/show.php/20874_1.jpg.html&quot; rel=&quot;nofollow&quot; target=&quot;_NEW&quot;&gt;\nhttp://0.picswan.com/show.php/20874_1.jpg.html&lt;/a&gt;\n","torrent":{"xt":"urn:btih:d1579d08a458f9d76de2f563062cfd9e5f6255b8","amp;dn":"NuruMassage+-+Asa+Akira+and+Kortney+Kane","amp;tr":["udp%3A%2F%2Ftracker.openbittorrent.com%3A80","udp%3A%2F%2Fopen.demonii.com%3A1337","udp%3A%2F%2Ftracker.coppersurfer.tk%3A6969","udp%3A%2F%2Fexodus.desync.com%3A6969"],"infoHash":"d1579d08a458f9d76de2f563062cfd9e5f6255b8","infoHashBuffer":{"type":"Buffer","data":[209,87,157,8,164,88,249,215,109,226,245,99,6,44,253,158,95,98,85,184]},"announce":[],"urlList":[]}}